README.rst
setup.py
Bashutils.egg-info/PKG-INFO
Bashutils.egg-info/SOURCES.txt
Bashutils.egg-info/dependency_links.txt
Bashutils.egg-info/top_level.txt
bashutils/__init__.py
bashutils/colors.py
bashutils/logmsg.py
bashutils/test/__init__.py
bashutils/test/test_color.py
bashutils/test/test_logmsg.py