Metadata-Version: 1.1
Name: Bashutils
Version: 0.0.3
Summary: Bash colors management and log system
Home-page: https://github.com/OlivierB/Bashutils.git
Author: Olivier BLIN
Author-email: olivier.oblin@gmail.com
License: GPLv3
Keywords: bash color log
Platform: UNKNOWN
Classifier: Environment :: Console
Classifier: Intended Audience :: Developers
Classifier: Natural Language :: English
Classifier: Operating System :: POSIX :: Linux
